Workbook
Name payment_transactions_export_1__2: shopify手数料試算!#REF!

Sheet レヴェニューシェア資料
A1: 売上
A2: 項目 | B2: 単価 | C2: 数量 | D2: 小計 | E2: 備考 | G2: 原価 | H2: 小計
A3: オンラインショップ 桐箱2碗 | B3: =ROUND(2000/1.1,0) -> 1818 | C3: 39 | D3: 35451 | G3: =18+620 -> 638 | H3: =G3*C3 -> 24882
A4: オンラインショップ 桐箱1碗 | B4: =ROUND(1000/1.1,0) -> 909 | C4: 13 | D4: 23634 | G4: =18+420 -> 438 | H4: =G4*C4 -> 5694
A5: オンラインショップ 紙袋2碗 | B5: =ROUND(250/1.1,0) -> 227 | C5: 35 | D5: 7000 | G5: =18+103 -> 121 | H5: =G5*C5 -> 4235
A6: オンラインショップ 紙袋1碗 | B6: =ROUND(220/1.1,0) -> 200 | C6: 7 | D6: 1589 | G6: =18+99 -> 117 | H6: =G6*C6 -> 819
A7: 売上合計 | C7: =SUM(C3:C6) -> 94 | D7: =SUM(D3:D6) -> 67674 | H7: =SUM(H3:H6) -> 35630
A9: 項目 | B9: 単価 | C9: 数量 | D9: 小計 | E9: 備考
D10: =C10*B10 -> 0
A12: 項目 | B12: 単価 | C12: 数量 | D12: 小計 | E12: 備考
A13: オンラインショップ SHUWAN陶胎漆器 | B13: 18000 | C13: 9 | D13: =C13*B13 -> 162000
A14: オンラインショップ SHUWAN | B14: 3900 | C14: 181 | D14: =C14*B14 -> 705900
A15: しゅわんグラス箱無し ロゴなし | B15: 2160 | C15: 12 | D15: =C15*B15 -> 25920
A16: SHUWAN箱なし | B16: 2650 | C16: 30 | D16: =C16*B16 -> 79500 | E16: ほうちょう
A17: SHUWAN箱なし | B17: 2440 | C17: 30 | D17: =C17*B17 -> 73200 | E17: 森ノ醸造所
A18: SHUWAN箱あり | B18: 2880 | C18: 40 | D18: =C18*B18 -> 115200 | E18: たまき酒店8 福司酒造10 東市酒店10 長谷川屋12
A19: SHUWAN箱あり | B19: 2640 | C19: 270 | D19: =C19*B19 -> 712800 | E19: 森田酒店12 パシオンエナチュール12 酒ハウスモリモト24 渡邉宗田商店12 エルスタイル90 LocalDesign90 酒泉洞堀一30
A20: 売上合計 | C20: =SUM(C13:C19) -> 572 | D20: =SUM(D10:D19) -> 1874520
A22: Amazon | B22: 平均単価 | C22: 数量 | D22: 小計 | E22: 備考
A23: アマゾン桐箱 1碗箱 原価 | B23: 420 | C23: 21 | D23: =C23*B23 -> 8820 | E23: アマゾン販売分木箱コスト
A24: アマゾン桐箱 2碗箱 原価 | B24: 620 | C24: 2 | D24: =C24*B24 -> 1240
A25: SHUWAN販売合計金額 | B25: =ROUND(D25/C25,0) -> 3978 | C25: 134 | D25: 533118 | E25: 11月分1個調整
A26: プロモーション割引合計 | D26: 6637
A27: Amazon手数料 | D27: 98628
A28: その他+ 保管料 | D28: -52940
A29: その他費用 | D29: 94746 | E29: 広告費用 月額登録料 プロモーション手数料
A30: 合計 | D30: =D25-D26-D27-D28-D29-D23-D24 -> 375987
A32: goooods | B32: 単価 | C32: 数量 | D32: 小計 | E32: 備考
A33: SHUWAN | B33: 3120 | C33: 0 | D33: =C33*B33 -> 0
A34: 取引手数料 | B34: 0 | C34: 0 | D34: =C34*B34 -> 0
A35: 事務手数料 | B35: 0 | C35: 0 | D35: =C35*B35 -> 0
A36: goooods収支合計 | D36: =D33-D34-D35 -> 0
A38: 変動費
A39: 項目 | B39: 単価 | C39: 数量 | D39: 小計 | E39: 備考
A40: 送料値引き | B40: 1000 | C40: 47 | D40: =B40*C40 -> 47000
A41: しゅわんグラス箱無し ロゴなし | B41: 460 | C41: =C15 -> 12 | D41: =B41*C41 -> 5520
A42: SHUWAN陶胎漆器 原価 | B42: 6500 | C42: =C13 -> 9 | D42: =B42*C42 -> 58500
A43: SHUWAN原価 | B43: 1260 | C43: =C20+C25+C33-C13-C15 -> 685 | D43: =B43*C43 -> 863100
A44: 桐箱&紙袋 原価 | B44: =ROUND(D44/C44,0) -> 379 | C44: =C7 -> 94 | D44: =H7 -> 35630
A45: 箱 | B45: 100 | C45: =C20+C25+C33-E45 -> 634 | D45: =B45*C45 -> 63400 | E45: 72
A46: 作家ロイヤリティ | B46: =ROUND(150/1.1,0) -> 136 | C46: =C20-E46 -> 551 | D46: =B46*C46 -> 74936 | E46: 21
A47: オンラインショップ手数料 | D47: =ROUND((D7+D14+D13)*0.0373,0) -> 34897 | E47: -0.0373
A48: そそぎ原価 | B48: 500 | C48: 0 | D48: =B48*C48 -> 0
A49: 変動費 計 | D49: =SUM(D40:D48) -> 1182983
A51: 項目 | B51: 金額
A52: 対象売上金額合計 | B52: =D20+D7+D52+D53+D54 -> 2059088 | D52: 34456 | E52: 11月 オンラインショップ桐箱紙袋
A53: 変動費合計 | B53: =D49 -> 1182983 | D53: 36020 | E53: 10月 オンラインショップ桐箱紙袋
A54: AMAZON収支 | B54: =D30 -> 375987 | D54: 46418 | E54: 9月 オンラインショップ桐箱紙袋
A55: goooods収支 | B55: =D36 -> 0
A56: 限界利益 | B56: =B52-B53+B54+B55 -> 1252092
A57: シンクロ(60%) | B57: =ROUND(B56*0.6,0) -> 751255
A58: 住吉酒販(40%) | B58: =B56*0.4 -> 500836.8
A60: ＊金額は税抜

Sheet Amazon詳細
A1: 日付 | B1: トランザクションステータス | C1: トランザクションの種類 | D1: 注文番号 | E1: 商品の詳細 | F1: 商品価格合計 | G1: プロモーション割引合計 | H1: Amazon手数料 | I1: その他 | J1: 合計 (JPY) | K1: 販売数量 | L1: 桐箱1 | M1: 桐箱2
A2: 46022 | B2: 支払い実行済み | C2: 注文に対する支払い | D2: 503-6649286-7039813 | E2: SHUWAN 酒器 おちょこ ぐい呑み 日本酒グラス 270ml 磁器 日本製 ... | F2: 4527 | G2: 0 | H2: -1248 | I2: 403 | J2: 3682 | K2: 1
A3: 46022 | B3: 支払い実行済み | C3: 注文に対する支払い | D3: 503-2937518-5362243 | E3: SHUWAN 酒器 おちょこ ぐい呑み 日本酒グラス 270ml 磁器 日本製 ... | F3: 4527 | G3: 0 | H3: -1248 | I3: 403 | J3: 3682 | K3: 1
A4: 46022 | B4: 支払い実行済み | C4: 注文に対する支払い | D4: 250-6296164-1357447 | E4: SHUWAN 酒器 おちょこ ぐい呑み 日本酒グラス 270ml 磁器 日本製 ... | F4: 4527 | G4: -91 | H4: -1248 | I4: 494 | J4: 3682 | K4: 1
A5: 46022 | B5: 支払い実行済み | C5: 注文に対する支払い | D5: 503-4336827-0155041 | E5: SHUWAN 酒器 おちょこ ぐい呑み 日本酒グラス 270ml 磁器 日本製 ... | F5: 4527 | G5: -418 | H5: -1248 | I5: 821 | J5: 3682 | K5: 1
A6: 46022 | B6: 支払い実行済み | C6: 注文に対する支払い | D6: 249-4150217-0376641 | E6: SHUWAN 酒器 おちょこ ぐい呑み 日本酒グラス 270ml 磁器 日本製 ... | F6: 4527 | G6: -91 | H6: -1248 | I6: 494 | J6: 3682 | K6: 1
A7: 46021 | B7: 支払い実行済み | C7: 注文に対する支払い | D7: 249-7793879-4760669 | E7: SHUWAN 酒器 おちょこ ぐい呑み 日本酒グラス 270ml 磁器 日本製 ... | F7: 4527 | G7: 0 | H7: -1248 | I7: 403 | J7: 3682 | K7: 1
A8: 46021 | B8: 支払い実行済み | C8: 注文に対する支払い | D8: 250-0598626-1308659 | E8: SHUWAN 酒器 おちょこ ぐい呑み 日本酒グラス 270ml 磁器 日本製 ... | F8: 4527 | G8: 0 | H8: -1248 | I8: 403 | J8: 3682 | K8: 1
A9: 46021 | B9: 支払い実行済み | C9: 注文に対する支払い | D9: 250-9035096-8239861 | E9: SHUWAN 酒器 おちょこ ぐい呑み 日本酒グラス 270ml 磁器 日本製 ... | F9: 4527 | G9: 0 | H9: -1248 | I9: 403 | J9: 3682 | K9: 1
A10: 46021 | B10: 支払い実行済み | C10: 注文に対する支払い | D10: 503-5183698-0671823 | E10: SHUWAN 酒器 おちょこ ぐい呑み 日本酒グラス 270ml 磁器 日本製 ... | F10: 4527 | G10: 0 | H10: -1248 | I10: 403 | J10: 3682 | K10: 1
A11: 46021 | B11: 支払い実行済み | C11: 注文に対する支払い | D11: 249-4023392-2258251 | E11: SHUWAN 酒器 おちょこ ぐい呑み 日本酒グラス 270ml 磁器 日本製 ... | F11: 4527 | G11: 0 | H11: -1248 | I11: 403 | J11: 3682 | K11: 1
A12: 46020 | B12: 支払い実行済み | C12: 注文に対する支払い | D12: 503-2943052-3533459 | E12: SHUWAN 酒器 おちょこ ぐい呑み 日本酒グラス 270ml 磁器 日本製 ... | F12: 4527 | G12: 0 | H12: -1602 | I12: 757 | J12: 3682 | K12: 1
A13: 46020 | B13: 支払い実行済み | C13: 注文に対する支払い | D13: 503-2195641-8505421 | E13: SHUWAN 酒器 おちょこ ぐい呑み 日本酒グラス 270ml 磁器 日本製 ... | F13: 4527 | G13: 0 | H13: -1248 | I13: 403 | J13: 3682 | K13: 1
... A30: 46016 | B30: 支払い実行済み | C30: 注文に対する支払い | D30: 503-9248144-3471037 | E30: SHUWAN 酒器 おちょこ ぐい呑み 日本酒グラス 270ml 磁器 日本製 ... | F30: 4527 | G30: 0 | H30: -434 | I30: 403 | J30: 4496 | K30: 1
A31: 46015 | B31: 支払い実行済み | C31: 注文に対する支払い | D31: 503-3307929-6851023 | E31: SHUWAN 酒器 おちょこ ぐい呑み 日本酒グラス 270ml 磁器 日本製 ... | F31: 5436 | G31: 0 | H31: -455 | I31: 484 | J31: 5465 | K31: 0 | L31: 1
A32: 46015 | B32: 支払い実行済み | C32: 注文に対する支払い | D32: 250-8649563-9152657 | E32: SHUWAN 酒器 おちょこ ぐい呑み 日本酒グラス 270ml 磁器 日本製 ... | F32: 4527 | G32: 0 | H32: -434 | I32: 403 | J32: 4496 | K32: 1
A33: 46015 | B33: 支払い実行済み | C33: 注文に対する支払い | D33: 503-2889803-9219809 | E33: SHUWAN 酒器 おちょこ ぐい呑み 日本酒グラス 270ml 磁器 日本製 ... | F33: 5436 | G33: 0 | H33: -455 | I33: 484 | J33: 5465 | K33: 0 | L33: 1
A34: 46015 | B34: 支払い実行済み | C34: 注文に対する支払い | D34: 503-5256721-1386202 | E34: SHUWAN 酒器 おちょこ ぐい呑み 日本酒グラス 270ml 磁器 日本製 ... | F34: 4527 | G34: 0 | H34: -434 | I34: 403 | J34: 4496 | K34: 1
A35: 46014 | B35: 支払い実行済み | C35: 注文に対する支払い | D35: 503-4611673-3275069 | E35: SHUWAN 酒器 おちょこ ぐい呑み 日本酒グラス 270ml 磁器 日本製 ... | F35: 5436 | G35: -680 | H35: -455 | I35: 620 | J35: 4921 | K35: 0 | L35: 1
A36: 46014 | B36: 支払い実行済み | C36: 注文に対する支払い | D36: 503-0857503-1815004 | E36: SHUWAN 酒器 おちょこ ぐい呑み 日本酒グラス 270ml 磁器 日本製 ... | F36: 4527 | G36: 0 | H36: -434 | I36: 403 | J36: 4496 | K36: 1
A37: 46014 | B37: 支払い実行済み | C37: 注文に対する支払い | D37: 250-2707319-4350211 | E37: SHUWAN 酒器 おちょこ ぐい呑み 日本酒グラス 270ml 磁器 日本製 ... | F37: 5436 | G37: 0 | H37: -455 | I37: 484 | J37: 5465 | K37: 0 | L37: 1
A38: 46014 | B38: 支払い実行済み | C38: 注文に対する支払い | D38: 249-0983870-9902246 | E38: SHUWAN 酒器 おちょこ ぐい呑み 日本酒グラス 270ml 磁器 日本製 ... | F38: 4527 | G38: 0 | H38: -434 | I38: 403 | J38: 4496 | K38: 1
A39: 46014 | B39: 支払い実行済み | C39: 注文に対する支払い | D39: 503-4377943-7123015 | E39: SHUWAN 酒器 おちょこ ぐい呑み 日本酒グラス 270ml 磁器 日本製 ... | F39: 4527 | G39: 0 | H39: -434 | I39: 403 | J39: 4496 | K39: 1
A40: 46013 | B40: 支払い実行済み | C40: 注文に対する支払い | D40: 250-3699519-1138225 | E40: SHUWAN 酒器 おちょこ ぐい呑み 日本酒グラス 270ml 磁器 日本製 ... | F40: 4527 | G40: 0 | H40: -434 | I40: 403 | J40: 4496 | K40: 1
A41: 46012 | B41: 支払い実行済み | C41: 注文に対する支払い | D41: 249-1043353-5968637 | E41: SHUWAN 酒器 おちょこ ぐい呑み 日本酒グラス 270ml 磁器 日本製 ... | F41: 4527 | G41: -182 | H41: -434 | I41: 585 | J41: 4496 | K41: 1
A42: 46012 | B42: 支払い実行済み | C42: 注文に対する支払い | D42: 249-3395405-0512640 | E42: SHUWAN 酒器 おちょこ ぐい呑み 日本酒グラス 270ml 磁器 日本製 ... | F42: 4527 | G42: -455 | H42: -434 | I42: 858 | J42: 4496 | K42: 1
A43: 46012 | B43: 支払い実行済み | C43: 注文に対する支払い | D43: 503-8236909-6670250 | E43: SHUWAN 酒器 おちょこ ぐい呑み 日本酒グラス 270ml 磁器 日本製 ... | F43: 5436 | G43: 0 | H43: -455 | I43: 484 | J43: 5465 | K43: 0 | L43: 1
A44: 46012 | B44: 支払い実行済み | C44: サービス料金 | D44: --- | E44: 広告費用 | F44: 0 | G44: 0 | H44: -55001 | I44: 0 | J44: -55001 | K44: 0 | L44: 0
A45: 46012 | B45: 支払い実行済み | C45: 注文に対する支払い | D45: 503-9729954-6523011 | E45: SHUWAN 酒器 おちょこ ぐい呑み 日本酒グラス 270ml 磁器 日本製 ... | F45: 4042 | G45: 0 | H45: -434 | I45: 360 | J45: 3968 | K45: 1
A46: 46012 | B46: 支払い実行済み | C46: 注文に対する支払い | D46: 249-4898620-5908668 | E46: SHUWAN 酒器 おちょこ ぐい呑み 日本酒グラス 270ml 磁器 日本製 ... | F46: 4527 | G46: 0 | H46: -434 | I46: 403 | J46: 4496 | K46: 1
A47: 46011 | B47: 支払い実行済み | C47: 注文に対する支払い | D47: 503-7349053-0193414 | E47: SHUWAN 酒器 おちょこ ぐい呑み 日本酒グラス 270ml 磁器 日本製 ... | F47: 5436 | G47: 0 | H47: -809 | I47: 838 | J47: 5465 | K47: 0 | L47: 1
A48: 46011 | B48: 支払い実行済み | C48: 注文に対する支払い | D48: 249-8938365-4542259 | E48: SHUWAN 酒器 おちょこ ぐい呑み 日本酒グラス 270ml 磁器 日本製 ... | F48: 4527 | G48: 0 | H48: -434 | I48: 403 | J48: 4496 | K48: 1
A49: 46011 | B49: 支払い実行済み | C49: 注文に対する支払い | D49: 250-9608473-1132636 | E49: SHUWAN 酒器 おちょこ ぐい呑み 日本酒グラス 270ml 磁器 日本製 ... | F49: 4527 | G49: 0 | H49: -434 | I49: 403 | J49: 4496 | K49: 1
A50: 46010 | B50: 支払い実行済み | C50: 注文に対する支払い | D50: 250-9970434-6254266 | E50: SHUWAN 酒器 おちょこ ぐい呑み 日本酒グラス 270ml 磁器 日本製 ... | F50: 4527 | G50: 0 | H50: -434 | I50: 403 | J50: 4496 | K50: 1
A51: 46010 | B51: 支払い実行済み | C51: 注文に対する支払い | D51: 503-0674528-8679058 | E51: SHUWAN 酒器 おちょこ ぐい呑み 日本酒グラス 270ml 磁器 日本製 ... | F51: 4893 | G51: -680 | H51: -455 | I51: 626 | J51: 4384 | K51: 0 | L51: 1
A52: 46010 | B52: 支払い実行済み | C52: 注文に対する支払い | D52: 249-9667583-0266254 | E52: SHUWAN 酒器 おちょこ ぐい呑み 日本酒グラス 270ml 磁器 日本製 ... | F52: 4527 | G52: 0 | H52: -434 | I52: 403 | J52: 4496 | K52: 1
A53: 46009 | B53: 支払い実行済み | C53: 注文に対する支払い | D53: 503-8485674-7466235 | E53: SHUWAN 酒器 おちょこ ぐい呑み 日本酒グラス 270ml 磁器 日本製 ... | F53: 4527 | G53: 0 | H53: -434 | I53: 403 | J53: 4496 | K53: 1
A54: 46008 | B54: 支払い実行済み | C54: 注文に対する支払い | D54: 250-2157862-8575055 | E54: SHUWAN 酒器 おちょこ ぐい呑み 日本酒グラス 270ml 磁器 日本製 ... | F54: 4527 | G54: -140 | H54: -434 | I54: 543 | J54: 4496 | K54: 1
A55: 46008 | B55: 支払い実行済み | C55: 注文に対する支払い | D55: 249-2036494-2058221 | E55: SHUWAN 酒器 おちょこ ぐい呑み 日本酒グラス 270ml 磁器 日本製 ... | F55: 4527 | G55: 0 | H55: -434 | I55: 403 | J55: 4496 | K55: 1
A56: 46008 | B56: 支払い実行済み | C56: 注文に対する支払い | D56: 503-2685575-5218253 | E56: SHUWAN 酒器 おちょこ ぐい呑み 日本酒グラス 270ml 磁器 日本製 ... | F56: 9055 | G56: 0 | H56: -868 | I56: 805 | J56: 8992 | K56: 2
A57: 46008 | B57: 支払い実行済み | C57: 注文に対する支払い | D57: 503-9281222-3938210 | E57: SHUWAN 酒器 おちょこ ぐい呑み 日本酒グラス 270ml 磁器 日本製 ... | F57: 4042 | G57: 0 | H57: -434 | I57: 360 | J57: 3968 | K57: 1
A58: 46007 | B58: 支払い実行済み | C58: 注文に対する支払い | D58: 249-8017187-9892606 | E58: SHUWAN 酒器 おちょこ ぐい呑み 日本酒グラス 270ml 磁器 日本製 ... | F58: 4527 | G58: 0 | H58: -434 | I58: 403 | J58: 4496 | K58: 1
A59: 46007 | B59: 支払い実行済み | C59: 注文に対する支払い | D59: 250-2705883-6849429 | E59: SHUWAN 酒器 おちょこ ぐい呑み 日本酒グラス 270ml 磁器 日本製 ... | F59: 4527 | G59: 0 | H59: -434 | I59: 403 | J59: 4496 | K59: 1
A60: 46007 | B60: 支払い実行済み | C60: 注文に対する支払い | D60: 250-5064597-6017418 | E60: SHUWAN 酒器 おちょこ ぐい呑み 日本酒グラス 270ml 磁器 日本製 ... | F60: 4893 | G60: 0 | H60: -455 | I60: 435 | J60: 4873 | K60: 0 | L60: 1
A61: 46007 | B61: 支払い実行済み | C61: 注文に対する支払い | D61: 503-9076013-1993428 | E61: SHUWAN 酒器 おちょこ ぐい呑み 日本酒グラス 270ml 磁器 日本製 ... | F61: 4042 | G61: -351 | H61: -434 | I61: 307 | J61: 3564 | K61: 1
A62: 46006 | B62: 支払い実行済み | C62: 注文に対する支払い | D62: 249-6340868-7150219 | E62: SHUWAN 酒器 おちょこ ぐい呑み 日本酒グラス 270ml 磁器 日本製 ... | F62: 5436 | G62: 0 | H62: -455 | I62: 484 | J62: 5465 | K62: 0 | L62: 1
A63: 46005 | B63: 支払い実行済み | C63: 注文に対する支払い | D63: 249-2110678-7147865 | E63: SHUWAN 酒器 おちょこ ぐい呑み 日本酒グラス 270ml 磁器 日本製 ... | F63: 4042 | G63: 0 | H63: -434 | I63: 360 | J63: 3968 | K63: 1
A64: 46005 | B64: 支払い実行済み | C64: 注文に対する支払い | D64: 249-6828347-6379000 | E64: SHUWAN 酒器 おちょこ ぐい呑み 日本酒グラス 270ml 磁器 日本製 ... | F64: 4042 | G64: 0 | H64: -434 | I64: 360 | J64: 3968 | K64: 1
A65: 46005 | B65: 支払い実行済み | C65: 注文に対する支払い | D65: 250-3975392-4579046 | E65: SHUWAN 酒器 おちょこ ぐい呑み 日本酒グラス 270ml 磁器 日本製 ... | F65: 4042 | G65: 0 | H65: -434 | I65: 360 | J65: 3968 | K65: 1
A66: 46005 | B66: 支払い実行済み | C66: 注文に対する支払い | D66: 503-7917590-3329452 | E66: SHUWAN 酒器 おちょこ ぐい呑み 日本酒グラス 270ml 磁器 日本製 ... | F66: 8084 | G66: 0 | H66: -868 | I66: 720 | J66: 7936 | K66: 2
A67: 46004 | B67: 支払い実行済み | C67: 注文に対する支払い | D67: 503-2680731-5728664 | E67: SHUWAN 酒器 おちょこ ぐい呑み 日本酒グラス 270ml 磁器 日本製 ... | F67: 4527 | G67: 0 | H67: -434 | I67: 403 | J67: 4496 | K67: 1
A68: 46004 | B68: 支払い実行済み | C68: 注文に対する支払い | D68: 503-3792065-4540623 | E68: SHUWAN 酒器 おちょこ ぐい呑み 日本酒グラス 270ml 磁器 日本製 ... | F68: 4893 | G68: 0 | H68: -455 | I68: 435 | J68: 4873 | K68: 0 | L68: 1
A69: 46004 | B69: 支払い実行済み | C69: 注文に対する支払い | D69: 250-6549794-9257447 | E69: SHUWAN 酒器 おちょこ ぐい呑み 日本酒グラス 270ml 磁器 日本製 ... | F69: 18484 | G69: 0 | H69: -1624 | I69: 1848 | J69: 18708 | K69: 0 | L69: 4
A70: 46004 | B70: 支払い実行済み | C70: 注文に対する支払い | D70: 503-6283355-7261462 | E70: SHUWAN 酒器 おちょこ ぐい呑み 日本酒グラス 270ml 磁器 日本製 ... | F70: 4893 | G70: 0 | H70: -809 | I70: 789 | J70: 4873 | K70: 0 | L70: 1
A71: 46003 | B71: 支払い実行済み | C71: 注文に対する支払い | D71: 249-9457170-4228621 | E71: SHUWAN 酒器 おちょこ ぐい呑み 日本酒グラス 270ml 磁器 日本製 ... | F71: 5436 | G71: 0 | H71: -455 | I71: 484 | J71: 5465 | K71: 0 | L71: 1
A72: 46003 | B72: 支払い実行済み | C72: 注文に対する支払い | D72: 503-3139464-4989448 | E72: SHUWAN 酒器 おちょこ ぐい呑み 日本酒グラス 270ml 磁器 日本製 ... | F72: 4042 | G72: 0 | H72: -434 | I72: 360 | J72: 3968 | K72: 1
A73: 46003 | B73: 支払い実行済み | C73: 注文に対する支払い | D73: 249-2561109-0583034 | E73: SHUWAN 酒器 おちょこ ぐい呑み 日本酒グラス 270ml 磁器 日本製 ... | F73: 4042 | G73: 0 | H73: -1160 | I73: 360 | J73: 3242 | K73: 1
A74: 46003 | B74: 支払い実行済み | C74: 注文に対する支払い | D74: 503-5356553-9439838 | E74: SHUWAN 酒器 おちょこ ぐい呑み 日本酒グラス 270ml 磁器 日本製 ... | F74: 4042 | G74: 0 | H74: -434 | I74: 360 | J74: 3968 | K74: 1
A75: 46003 | B75: 支払い実行済み | C75: 注文に対する支払い | D75: 249-0721221-4697428 | E75: SHUWAN 酒器 おちょこ ぐい呑み 日本酒グラス 270ml 磁器 日本製 ... | F75: 4042 | G75: 0 | H75: -434 | I75: 360 | J75: 3968 | K75: 1
A76: 46002 | B76: 支払い実行済み | C76: 注文に対する支払い | D76: 249-6847165-4231863 | E76: SHUWAN 酒器 おちょこ ぐい呑み 日本酒グラス 270ml 磁器 日本製 ... | F76: 4042 | G76: 0 | H76: -434 | I76: 360 | J76: 3968 | K76: 1
A77: 46002 | B77: 支払い実行済み | C77: 注文に対する支払い | D77: 503-6598659-2191830 | E77: SHUWAN 酒器 おちょこ ぐい呑み 日本酒グラス 270ml 磁器 日本製 ... | F77: 8084 | G77: 0 | H77: -868 | I77: 720 | J77: 7936 | K77: 2
A78: 46002 | B78: 支払い実行済み | C78: 注文に対する支払い | D78: 503-1949220-5390220 | E78: SHUWAN 酒器 おちょこ ぐい呑み 日本酒グラス 270ml 磁器 日本製 ... | F78: 9785 | G78: 0 | H78: -434 | I78: 871 | J78: 10222 | K78: 0 | L78: 0 | M78: 1
A79: 46002 | B79: 支払い実行済み | C79: 注文に対する支払い | D79: 250-9683564-6757404 | E79: SHUWAN 酒器 おちょこ ぐい呑み 日本酒グラス 270ml 磁器 日本製 ... | F79: 4893 | G79: 0 | H79: -455 | I79: 435 | J79: 4873 | K79: 0 | L79: 1
A80: 46002 | B80: 支払い実行済み | C80: 注文に対する支払い | D80: 250-4004056-3402226 | E80: SHUWAN 酒器 おちょこ ぐい呑み 日本酒グラス 270ml 磁器 日本製 ... | F80: 8084 | G80: 0 | H80: -2320 | I80: 720 | J80: 6484 | K80: 2
A81: 46002 | B81: 支払い実行済み | C81: 注文に対する支払い | D81: 249-1071006-1611857 | E81: SHUWAN 酒器 おちょこ ぐい呑み 日本酒グラス 270ml 磁器 日本製 ... | F81: 4042 | G81: 0 | H81: -1160 | I81: 360 | J81: 3242 | K81: 1
A82: 46002 | B82: 支払い実行済み | C82: 注文に対する支払い | D82: 249-3184163-2910201 | E82: SHUWAN 酒器 おちょこ ぐい呑み 日本酒グラス 270ml 磁器 日本製 ... | F82: 8084 | G82: -1162 | H82: -2188 | I82: 1074 | J82: 5808 | K82: 2
A83: 46001 | B83: 支払い実行済み | C83: 注文に対する支払い | D83: 249-7211913-5334235 | E83: SHUWAN 酒器 おちょこ ぐい呑み 日本酒グラス 270ml 磁器 日本製 ... | F83: 4042 | G83: 0 | H83: -434 | I83: 360 | J83: 3968 | K83: 1
A84: 46001 | B84: 支払い実行済み | C84: 注文に対する支払い | D84: 249-2844105-2897465 | E84: SHUWAN 酒器 おちょこ ぐい呑み 日本酒グラス 270ml 磁器 日本製 ... | F84: 4893 | G84: 0 | H84: -455 | I84: 435 | J84: 4873 | K84: 0 | L84: 1
A85: 46001 | B85: 支払い実行済み | C85: 注文に対する支払い | D85: 250-2745361-5908656 | E85: SHUWAN 酒器 おちょこ ぐい呑み 日本酒グラス 270ml 磁器 日本製 ... | F85: 4042 | G85: 0 | H85: -1160 | I85: 360 | J85: 3242 | K85: 1
A86: 46001 | B86: 支払い実行済み | C86: 注文に対する支払い | D86: 249-9433497-8392626 | E86: SHUWAN 酒器 おちょこ ぐい呑み 日本酒グラス 270ml 磁器 日本製 ... | F86: 4042 | G86: 0 | H86: -1514 | I86: 714 | J86: 3242 | K86: 1
A87: 46001 | B87: 支払い実行済み | C87: 注文に対する支払い | D87: 503-0978931-4551020 | E87: SHUWAN 酒器 おちょこ ぐい呑み 日本酒グラス 270ml 磁器 日本製 ... | F87: 9785 | G87: 0 | H87: -2668 | I87: 871 | J87: 7988 | K87: 0 | L87: 0 | M87: 1
A88: 46001 | B88: 支払い実行済み | C88: サービス料金 | D88: --- | E88: 月額登録料： | F88: 0 | G88: 0 | H88: -5390 | I88: 0 | J88: -5390 | K88: 0 | L88: 0
A89: 46000 | B89: 支払い実行済み | C89: 注文に対する支払い | D89: 250-5134036-1823860 | E89: SHUWAN 酒器 おちょこ ぐい呑み 日本酒グラス 270ml 磁器 日本製 ... | F89: 4042 | G89: -182 | H89: -1160 | I89: 542 | J89: 3242 | K89: 1
A90: 45999 | B90: 支払い実行済み | C90: 注文に対する支払い | D90: 249-4168228-6351862 | E90: SHUWAN 酒器 おちょこ ぐい呑み 日本酒グラス 270ml 磁器 日本製 ... | F90: 16167 | G90: 0 | H90: -4640 | I90: 1441 | J90: 12968 | K90: 4
A91: 45999 | B91: 支払い実行済み | C91: 注文に対する支払い | D91: 503-2013545-5135033 | E91: SHUWAN 酒器 おちょこ ぐい呑み 日本酒グラス 270ml 磁器 日本製 ... | F91: 4042 | G91: 0 | H91: -1160 | I91: 360 | J91: 3242 | K91: 1
A92: 45999 | B92: 支払い実行済み | C92: 注文に対する支払い | D92: 503-7751489-9509403 | E92: SHUWAN 酒器 おちょこ ぐい呑み 日本酒グラス 270ml 磁器 日本製 ... | F92: 4042 | G92: 0 | H92: -1160 | I92: 360 | J92: 3242 | K92: 1
A93: 45998 | B93: 支払い実行済み | C93: 注文に対する支払い | D93: 250-4650511-7734228 | E93: SHUWAN 酒器 おちょこ ぐい呑み 日本酒グラス 270ml 磁器 日本製 ... | F93: 4042 | G93: -418 | H93: -1160 | I93: 778 | J93: 3242 | K93: 1
A94: 45998 | B94: 支払い実行済み | C94: 注文に対する支払い | D94: 249-7888061-2015835 | E94: SHUWAN 酒器 おちょこ ぐい呑み 日本酒グラス 270ml 磁器 日本製 ... | F94: 4893 | G94: 0 | H94: -1334 | I94: 435 | J94: 3994 | K94: 0 | L94: 1
A95: 45998 | B95: 支払い実行済み | C95: 注文に対する支払い | D95: 249-9837720-3591833 | E95: SHUWAN 酒器 おちょこ ぐい呑み 日本酒グラス 270ml 磁器 日本製 ... | F95: 4042 | G95: 0 | H95: -1160 | I95: 360 | J95: 3242 | K95: 1
A96: 45998 | B96: 支払い実行済み | C96: サービス料金 | D96: --- | E96: FBA保管手数料： | F96: 0 | G96: 0 | H96: 0 | I96: -1201 | J96: -1201 | K96: 0 | L96: 0
A97: 45997 | B97: 支払い実行済み | C97: 注文に対する支払い | D97: 250-6265678-5643029 | E97: SHUWAN 酒器 おちょこ ぐい呑み 日本酒グラス 270ml 磁器 日本製 ... | F97: 4042 | G97: 0 | H97: -1160 | I97: 360 | J97: 3242 | K97: 1
A98: 45997 | B98: 支払い実行済み | C98: 注文に対する支払い | D98: 503-3715259-9108626 | E98: SHUWAN 酒器 おちょこ ぐい呑み 日本酒グラス 270ml 磁器 日本製 ... | F98: 4042 | G98: 0 | H98: -1160 | I98: 360 | J98: 3242 | K98: 1
A99: 45997 | B99: 支払い実行済み | C99: 注文に対する支払い | D99: 249-1337308-1559807 | E99: SHUWAN 酒器 おちょこ ぐい呑み 日本酒グラス 270ml 磁器 日本製 ... | F99: 4042 | G99: 0 | H99: -1160 | I99: 360 | J99: 3242 | K99: 1
A100: 45997 | B100: 支払い実行済み | C100: 注文に対する支払い | D100: 250-8033166-3884610 | E100: SHUWAN 酒器 おちょこ ぐい呑み 日本酒グラス 270ml 磁器 日本製 ... | F100: 4893 | G100: 0 | H100: -1334 | I100: 435 | J100: 3994 | K100: 0 | L100: 1
A101: 45997 | B101: 支払い実行済み | C101: 注文に対する支払い | D101: 503-4914983-6451842 | E101: SHUWAN 酒器 おちょこ ぐい呑み 日本酒グラス 270ml 磁器 日本製 ... | F101: 4042 | G101: 0 | H101: -1160 | I101: 360 | J101: 3242 | K101: 1
A102: 45997 | B102: 支払い実行済み | C102: 注文に対する支払い | D102: 249-0662433-6281460 | E102: SHUWAN 酒器 おちょこ ぐい呑み 日本酒グラス 270ml 磁器 日本製 ... | F102: 4042 | G102: 0 | H102: -1160 | I102: 360 | J102: 3242 | K102: 1
A103: 45997 | B103: 支払い実行済み | C103: 注文に対する支払い | D103: 249-1226716-0483042 | E103: SHUWAN 酒器 おちょこ ぐい呑み 日本酒グラス 270ml 磁器 日本製 ... | F103: 4042 | G103: -209 | H103: -1160 | I103: 569 | J103: 3242 | K103: 1
A104: 45997 | B104: 支払い実行済み | C104: 注文に対する支払い | D104: 249-3087859-9163022 | E104: SHUWAN 酒器 おちょこ ぐい呑み 日本酒グラス 270ml 磁器 日本製 ... | F104: 4042 | G104: 0 | H104: -1160 | I104: 360 | J104: 3242 | K104: 1
A105: 45996 | B105: 支払い実行済み | C105: 注文に対する支払い | D105: 503-2463232-3152641 | E105: SHUWAN 酒器 おちょこ ぐい呑み 日本酒グラス 270ml 磁器 日本製 ... | F105: 4042 | G105: 0 | H105: -1160 | I105: 360 | J105: 3242 | K105: 1
A106: 45995 | B106: 支払い実行済み | C106: 注文に対する支払い | D106: 249-2572055-3763827 | E106: SHUWAN 酒器 おちょこ ぐい呑み 日本酒グラス 270ml 磁器 日本製 ... | F106: 4042 | G106: 0 | H106: -1160 | I106: 360 | J106: 3242 | K106: 1
A107: 45995 | B107: 支払い実行済み | C107: 注文に対する支払い | D107: 250-9432919-9326254 | E107: SHUWAN 酒器 おちょこ ぐい呑み 日本酒グラス 270ml 磁器 日本製 ... | F107: 4042 | G107: 0 | H107: -1160 | I107: 360 | J107: 3242 | K107: 1
A108: 45994 | B108: 支払い実行済み | C108: 注文に対する支払い | D108: 503-5051714-0721457 | E108: SHUWAN 酒器 おちょこ ぐい呑み 日本酒グラス 270ml 磁器 日本製 ... | F108: 4042 | G108: -806 | H108: -1094 | I108: 762 | J108: 2904 | K108: 1
A109: 45994 | B109: 支払い実行済み | C109: 注文に対する支払い | D109: 250-7320542-5241406 | E109: SHUWAN 酒器 おちょこ ぐい呑み 日本酒グラス 270ml 磁器 日本製 ... | F109: 4042 | G109: 0 | H109: -1160 | I109: 360 | J109: 3242 | K109: 1
A110: 45994 | B110: 支払い実行済み | C110: 注文に対する支払い | D110: 250-9254669-7517411 | E110: SHUWAN 酒器 おちょこ ぐい呑み 日本酒グラス 270ml 磁器 日本製 ... | F110: 8084 | G110: 0 | H110: -2320 | I110: 720 | J110: 6484 | K110: 2
A111: 45994 | B111: 支払い実行済み | C111: 注文に対する支払い | D111: 249-8880604-3652612 | E111: SHUWAN 酒器 おちょこ ぐい呑み 日本酒グラス 270ml 磁器 日本製 ... | F111: 4042 | G111: 0 | H111: -1160 | I111: 360 | J111: 3242 | K111: 1
A112: 45994 | B112: 支払い実行済み | C112: 注文に対する支払い | D112: 250-9847926-9547853 | E112: SHUWAN 酒器 おちょこ ぐい呑み 日本酒グラス 270ml 磁器 日本製 ... | F112: 4042 | G112: 0 | H112: -1160 | I112: 360 | J112: 3242 | K112: 1
... A114: 45993 | B114: 支払い実行済み | C114: 注文に対する支払い | D114: 503-4346602-5188612 | E114: SHUWAN 酒器 おちょこ ぐい呑み 日本酒グラス 270ml 磁器 日本製 ... | F114: 4042 | G114: 0 | H114: -1160 | I114: 360 | J114: 3242 | K114: 1
A115: 45993 | B115: 支払い実行済み | C115: 注文に対する支払い | D115: 249-9883130-8115834 | E115: SHUWAN 酒器 おちょこ ぐい呑み 日本酒グラス 270ml 磁器 日本製 ... | F115: 4893 | G115: 0 | H115: -1334 | I115: 435 | J115: 3994 | K115: 0 | L115: 1
A116: 45993 | B116: 支払い実行済み | C116: 注文に対する支払い | D116: 503-4230563-9535827 | E116: SHUWAN 酒器 おちょこ ぐい呑み 日本酒グラス 270ml 磁器 日本製 ... | F116: 4042 | G116: 0 | H116: -1160 | I116: 360 | J116: 3242 | K116: 1
A117: 45993 | B117: 支払い実行済み | C117: サービス料金 | D117: --- | E117: 広告費用 | F117: 0 | G117: 0 | H117: -36469 | I117: 0 | J117: -36469 | K117: 0 | L117: 0
...

Sheet 留保中1月請求時確認
A1: 日付 | B1: トランザクションステータス | C1: トランザクションの種類 | D1: 注文番号 | E1: 商品の詳細 | F1: 商品価格合計 | G1: プロモーション割引合計 | H1: Amazon手数料 | I1: その他 | J1: 合計 (JPY) | K1: 番号確認
A2: 46021 | B2: 留保中 | C2: 注文に対する支払い | D2: 249-3243967-2306223 | E2: SHUWAN 酒器 おちょこ ぐい呑み 日本酒グラス 270ml 磁器 日本製 ... | F2: 9054 | G2: -1612 | H2: -2346 | I2: 1512 | J2: 6608 | K2: =VLOOKUP(D2,Amazon詳細!D:D,1,0) -> #N/A
A3: 46021 | B3: 留保中 | C3: 注文に対する支払い | D3: 250-9741592-9678248 | E3: SHUWAN 酒器 おちょこ ぐい呑み 日本酒グラス 270ml 磁器 日本製 ... | F3: 4527 | G3: 0 | H3: -1248 | I3: 403 | J3: 3682 | K3: =VLOOKUP(D3,Amazon詳細!D:D,1,0) -> #N/A
A4: 46019 | B4: 留保中 | C4: 注文に対する支払い | D4: 249-2504865-6667055 | E4: SHUWAN 酒器 おちょこ ぐい呑み 日本酒グラス 270ml 磁器 日本製 ... | F4: 4527 | G4: 0 | H4: -1248 | I4: 403 | J4: 3682 | K4: =VLOOKUP(D4,Amazon詳細!D:D,1,0) -> #N/A
A5: 46019 | B5: 留保中 | C5: 注文に対する支払い | D5: 250-3052206-1178220 | E5: SHUWAN 酒器 おちょこ ぐい呑み 日本酒グラス 270ml 磁器 日本製 ... | F5: 4527 | G5: 0 | H5: -1248 | I5: 403 | J5: 3682 | K5: =VLOOKUP(D5,Amazon詳細!D:D,1,0) -> #N/A
A6: 46019 | B6: 留保中 | C6: 注文に対する支払い | D6: 503-1737750-3501452 | E6: SHUWAN 酒器 おちょこ ぐい呑み 日本酒グラス 270ml 磁器 日本製 ... | F6: 5436 | G6: 0 | H6: -1432 | I6: 484 | J6: 4488 | K6: =VLOOKUP(D6,Amazon詳細!D:D,1,0) -> #N/A
A7: 46018 | B7: 留保中 | C7: 注文に対する支払い | D7: 249-2438002-8910245 | E7: SHUWAN 酒器 おちょこ ぐい呑み 日本酒グラス 270ml 磁器 日本製 ... | F7: 10873 | G7: 0 | H7: -2864 | I7: 967 | J7: 8976 | K7: =VLOOKUP(D7,Amazon詳細!D:D,1,0) -> #N/A
A8: 46018 | B8: 留保中 | C8: 注文に対する支払い | D8: 249-3263559-4345455 | E8: SHUWAN 酒器 おちょこ ぐい呑み 日本酒グラス 270ml 磁器 日本製 ... | F8: 18109 | G8: 0 | H8: -4992 | I8: 1611 | J8: 14728 | K8: =VLOOKUP(D8,Amazon詳細!D:D,1,0) -> #N/A
A9: 46018 | B9: 留保中 | C9: 注文に対する支払い | D9: 249-6490746-5346226 | E9: SHUWAN 酒器 おちょこ ぐい呑み 日本酒グラス 270ml 磁器 日本製 ... | F9: 4527 | G9: -418 | H9: -1248 | I9: 821 | J9: 3682 | K9: =VLOOKUP(D9,Amazon詳細!D:D,1,0) -> #N/A
A10: 46018 | B10: 留保中 | C10: 注文に対する支払い | D10: 503-3331991-7543014 | E10: SHUWAN 酒器 おちょこ ぐい呑み 日本酒グラス 270ml 磁器 日本製 ... | F10: 4527 | G10: 0 | H10: -1248 | I10: 403 | J10: 3682 | K10: =VLOOKUP(D10,Amazon詳細!D:D,1,0) -> #N/A
A11: 46018 | B11: 留保中 | C11: 注文に対する支払い | D11: 250-3143183-3017401 | E11: SHUWAN 酒器 おちょこ ぐい呑み 日本酒グラス 270ml 磁器 日本製 ... | F11: 4527 | G11: 0 | H11: -1248 | I11: 403 | J11: 3682 | K11: =VLOOKUP(D11,Amazon詳細!D:D,1,0) -> #N/A
A12: 46018 | B12: 留保中 | C12: 注文に対する支払い | D12: 503-7270054-5899043 | E12: SHUWAN 酒器 おちょこ ぐい呑み 日本酒グラス 270ml 磁器 日本製 ... | F12: 4527 | G12: 0 | H12: -1248 | I12: 403 | J12: 3682 | K12: =VLOOKUP(D12,Amazon詳細!D:D,1,0) -> #N/A
A13: 46018 | B13: 留保中 | C13: 注文に対する支払い | D13: 250-0199547-2590275 | E13: SHUWAN 酒器 おちょこ ぐい呑み 日本酒グラス 270ml 磁器 日本製 ... | F13: 4527 | G13: 0 | H13: -1248 | I13: 403 | J13: 3682 | K13: =VLOOKUP(D13,Amazon詳細!D:D,1,0) -> #N/A
... A15: 45992 | B15: 留保中 | C15: 注文に対する支払い | D15: 503-4855838-1050230 | E15: SHUWAN 酒器 おちょこ ぐい呑み 日本酒グラス 270ml 磁器 日本製 ... | F15: 4893 | G15: 0 | H15: -1334 | I15: 435 | J15: 3994 | K15: =VLOOKUP(D15,Amazon詳細!D:D,1,0) -> #N/A
K16: =VLOOKUP(D16,Amazon詳細!D:D,1,0) -> #N/A
K17: =VLOOKUP(D17,Amazon詳細!D:D,1,0) -> #N/A
K18: =VLOOKUP(D18,Amazon詳細!D:D,1,0) -> #N/A
K19: =VLOOKUP(D19,Amazon詳細!D:D,1,0) -> #N/A
K20: =VLOOKUP(D20,Amazon詳細!D:D,1,0) -> #N/A
K21: =VLOOKUP(D21,Amazon詳細!D:D,1,0) -> #N/A
K22: =VLOOKUP(D22,Amazon詳細!D:D,1,0) -> #N/A
K23: =VLOOKUP(D23,Amazon詳細!D:D,1,0) -> #N/A
K24: =VLOOKUP(D24,Amazon詳細!D:D,1,0) -> #N/A
K25: =VLOOKUP(D25,Amazon詳細!D:D,1,0) -> #N/A
K26: =VLOOKUP(D26,Amazon詳細!D:D,1,0) -> #N/A

Sheet shopify手数料試算
A1: Payout Date | B1: Status | C1: Charges | D1: Refunds | E1: Adjustments | F1: Marketplace Sales Tax | G1: Advances | H1: Reserved Funds | I1: Fees | J1: Retried Amount | K1: Total | L1: Currency | M1: 手数料率
A2: 45681 | B2: paid | C2: 55220 | D2: 0 | E2: 0 | F2: 0 | G2: 0 | H2: 0 | I2: 1993 | J2: 0 | K2: 53227 | L2: JPY | M2: =I2/K2 -> 0.037443403
A3: 45674 | B3: paid | C3: 15180 | D3: 0 | E3: 0 | F3: 0 | G3: 0 | H3: 0 | I3: 540 | J3: 0 | K3: 14640 | L3: JPY | M3: =I3/K3 -> 0.036885246
A4: 45667 | B4: paid | C4: 55220 | D4: 0 | E4: 0 | F4: 0 | G4: 0 | H4: 0 | I4: 1962 | J4: 0 | K4: 53258 | L4: JPY | M4: =I4/K4 -> 0.036839536
A5: 45663 | B5: paid | C5: 50820 | D5: 0 | E5: 0 | F5: 0 | G5: 0 | H5: 0 | I5: 1805 | J5: 0 | K5: 49015 | L5: JPY | M5: =I5/K5 -> 0.036825462
A6: 45653 | B6: paid | C6: 91300 | D6: 0 | E6: 0 | F6: 0 | G6: 0 | H6: 0 | I6: 3273 | J6: 0 | K6: 88027 | L6: JPY | M6: =I6/K6 -> 0.037181774
A7: 45646 | B7: paid | C7: 52360 | D7: 0 | E7: 0 | F7: 0 | G7: 0 | H7: 0 | I7: 1909 | J7: 0 | K7: 50451 | L7: JPY | M7: =I7/K7 -> 0.037838695
A8: 45639 | B8: paid | C8: 39380 | D8: 0 | E8: 0 | F8: 0 | G8: 0 | H8: 0 | I8: 1400 | J8: 0 | K8: 37980 | L8: JPY | M8: =I8/K8 -> 0.036861506
A9: 45632 | B9: paid | C9: 28160 | D9: 0 | E9: 0 | F9: 0 | G9: 0 | H9: 0 | I9: 1000 | J9: 0 | K9: 27160 | L9: JPY | M9: =I9/K9 -> 0.036818851
A10: 45625 | B10: paid | C10: 32120 | D10: 0 | E10: 0 | F10: 0 | G10: 0 | H10: 0 | I10: 1141 | J10: 0 | K10: 30979 | L10: JPY | M10: =I10/K10 -> 0.036831402
A11: 45618 | B11: paid | C11: 37180 | D11: 0 | E11: 0 | F11: 0 | G11: 0 | H11: 0 | I11: 1321 | J11: 0 | K11: 35859 | L11: JPY | M11: =I11/K11 -> 0.036838729
A12: 45611 | B12: paid | C12: 61380 | D12: 0 | E12: 0 | F12: 0 | G12: 0 | H12: 0 | I12: 2244 | J12: 0 | K12: 59136 | L12: JPY | M12: =I12/K12 -> 0.037946429
A13: 45604 | B13: paid | C13: 15180 | D13: 0 | E13: 0 | F13: 0 | G13: 0 | H13: 0 | I13: 540 | J13: 0 | K13: 14640 | L13: JPY | M13: =I13/K13 -> 0.036885246
... A16: 45576 | B16: paid | C16: 254320 | D16: 0 | E16: 0 | F16: 0 | G16: 0 | H16: 0 | I16: 9246 | J16: 0 | K16: 245074 | L16: JPY | M16: =I16/K16 -> 0.03772738
A17: 合計 | I17: =SUM(I2:I16) -> 35731 | K17: =SUM(K2:K16) -> 958229 | M17: =I17/K17 -> 0.037288581
